goku_STT/_int_.py
goku_STT-0.1.dist-info/METADATA
goku_STT-0.1.dist-info/WHEEL
goku_STT-0.1.dist-info/top_level.txt
goku_STT-0.1.dist-info/RECORD
